threat_db/__init__.py
threat_db/admincli.py
threat_db/api.py
threat_db/base-schema.graphql
threat_db/cli.py
threat_db/client.py
threat_db/config.py
threat_db/graphclient.py
threat_db/loader.py
threat_db/logger.py
threat_db/queries.py
threat_db/utils.py
threat_db-0.6.3.dist-info/METADATA
threat_db-0.6.3.dist-info/entry_points.txt
threat_db-0.6.3.dist-info/WHEEL
threat_db-0.6.3.dist-info/LICENSE
threat_db-0.6.3.dist-info/RECORD
