Metadata-Version: 2.1
Name: threat-db
Version: 0.6.3
Summary: A graphql server for vulnerabilities powered by dgraph
License: Apache-2.0
Author: Team AppThreat
Author-email: cloud@appthreat.com
Requires-Python: >=3.7,<3.11
Classifier: Development Status :: 5 - Production/Stable
Classifier: Intended Audience :: Developers
Classifier: Intended Audience :: System Administrators
Classifier: License :: OSI Approved :: Apache Software License
Classifier: Operating System :: OS Independent
Classifier: Programming Language :: Python :: 3
Classifier: Programming Language :: Python :: 3.7
Classifier: Programming Language :: Python :: 3.8
Classifier: Programming Language :: Python :: 3.9
Classifier: Programming Language :: Python :: 3.10
Classifier: Programming Language :: Python :: 3.10
Classifier: Programming Language :: Python :: 3.8
Classifier: Programming Language :: Python :: 3.9
Classifier: Topic :: Security
Classifier: Topic :: Utilities
Requires-Dist: flask (>=2.2.2,<3.0.0)
Requires-Dist: flask-jwt-extended (>=4.4.4,<5.0.0)
Requires-Dist: gql[all] (>=3.4.0,<4.0.0)
Requires-Dist: grpcio (>=1.51.1,<2.0.0)
Requires-Dist: itsdangerous (>=2.1.2,<3.0.0)
Requires-Dist: orjson (>=3.8.5,<4.0.0)
Requires-Dist: packageurl-python (>=0.10.4,<0.11.0)
Requires-Dist: protobuf (>=3.20.1,<4.0.0)
Requires-Dist: pydgraph (>=21.3.2,<22.0.0)
Requires-Dist: rich (>=13.3.1,<14.0.0)
Requires-Dist: uwsgi (>=2.0.21,<3.0.0)
